vfs_appointment_bot/main.py
vfs_appointment_bot/notification/email_client.py
vfs_appointment_bot/notification/notification_client.py
vfs_appointment_bot/notification/notification_client_factory.py
vfs_appointment_bot/notification/telegram_client.py
vfs_appointment_bot/notification/twilio_client.py
vfs_appointment_bot/utils/config_reader.py
vfs_appointment_bot/utils/date_utils.py
vfs_appointment_bot/utils/timer.py
vfs_appointment_bot/vfs_bot/vfs_bot.py
vfs_appointment_bot/vfs_bot/vfs_bot_de.py
vfs_appointment_bot/vfs_bot/vfs_bot_factory.py
vfs_appointment_bot/vfs_bot/vfs_bot_it.py
vfs_appointment_bot-1.1.1.dist-info/LICENSE
vfs_appointment_bot-1.1.1.dist-info/METADATA
vfs_appointment_bot-1.1.1.dist-info/WHEEL
vfs_appointment_bot-1.1.1.dist-info/entry_points.txt
vfs_appointment_bot-1.1.1.dist-info/RECORD
