Metadata-Version: 2.1
Name: vfs-appointment-bot
Version: 1.1.1
Summary: VFS Appointment Bot - This script automates checking for appointments at VFS Global offices in a specified country.
License: MIT
Keywords: vfs,vfs-bot,vfs-appointment-bot,visa-appointment-bot
Author: Ranjan Mohanty
Author-email: ranjan@duck.com
Requires-Python: >=3.9,<4.0
Classifier: License :: OSI Approved :: MIT License
Classifier: Programming Language :: Python :: 3
Classifier: Programming Language :: Python :: 3.9
Classifier: Programming Language :: Python :: 3.10
Classifier: Programming Language :: Python :: 3.11
Classifier: Programming Language :: Python :: 3.12
Requires-Dist: playwright (>=1.43.0,<2.0.0)
Requires-Dist: playwright-stealth (>=1.0.6,<2.0.0)
Requires-Dist: tqdm (>=4.66.2,<5.0.0)
Requires-Dist: twilio (>=9.0.4,<10.0.0)
Project-URL: homepage, https://github.com/ranjan-mohanty/vfs-appointment-bot/blob/main
Project-URL: repository, https://github.com/ranjan-mohanty/vfs-appointment-bot/blob/main/README.md
